histo.py
setup.py
histo.egg-info/PKG-INFO
histo.egg-info/SOURCES.txt
histo.egg-info/dependency_links.txt
histo.egg-info/entry_points.txt
histo.egg-info/top_level.txt