Metadata-Version: 1.0
Name: histo
Version: 0.1
Summary: Statistical histograms based on Sturges rule
Home-page: UNKNOWN
Author: Pavel Paulau
Author-email: pavel.paulau@gmail.com
License: UNKNOWN
Platform: UNKNOWN
